setup.py
HD44780.egg-info/PKG-INFO
HD44780.egg-info/SOURCES.txt
HD44780.egg-info/dependency_links.txt
HD44780.egg-info/top_level.txt
hd44780/__init__.py
hd44780/backends.py
hd44780/inputs.py
hd44780/lcd.py
hd44780/metadata.py
hd44780/utils.py