Metadata-Version: 1.0
Name: HD44780
Version: 1.1.2
Summary: A library for controlling HD44780 compatible character LCDs
Home-page: https://github.com/Mezgrman/HD44780
Author: Julian Metzler
Author-email: contact@mezgrman.de
License: AGPLv3
Keywords: library lcd display hd44780 interface
Platform: UNKNOWN
